{"cameraMode":{"drawMode":0,"name":"Shaded","section":"Shading Mode"},"sceneLighting":true,"audioPlay":false,"sceneViewState":{"m_AlwaysRefresh":false,"showFog":true,"showSkybox":true,"showFlares":true,"showImageEffects":true,"showParticleSystems":true,"showVisualEffectGraphs":true,"m_FxEnabled":true},"in2DMode":false,"pivot":{"x":-2.144839286804199,"y":-4.30167293548584,"z":-4.778192520141602},"rotation":{"x":-0.09833618253469467,"y":0.8851545453071594,"z":-0.21831776201725007,"w":-0.39873966574668887},"size":11.777971267700196,"orthographic":false}